{"result":{"offset":0,"limit":10000,"count":82,"sort":"","results":[{"_id":"1","AC_NO":"104005289","ST_NO":"1","SNO":"159","APPMODE":"0","X":"308573.756","Y":"2771054.096","APPTIME":"1051020091918","APP_NAME":"衛工處","C_NAME":"信義","ADDR":"永吉路433號至527號、中坡北路33號至松山路119巷口、中坡北路37巷口、中坡北路43巷口、永吉路517巷8弄口、松山路181巷口、松山路191巷口、松山路195至199號","CB_DA":"1040721","CE_DA":"1051031","CO_TI":"日間施工9時至16時30分","TC_MA":"李彥蔚","TC_TL":"0931153761","TC_MA3":"邱建誠","TC_TL3":"0913550560","NPURP":"市政建設","DTYPE":null},{"_id":"2","AC_NO":"104007654","ST_NO":"1","SNO":"52","APPMODE":"0","X":"299789.426","Y":"2769020.465","APPTIME":"1051020090213","APP_NAME":"衛工處","C_NAME":"萬華","ADDR":"西藏路277號附近地區","CB_DA":"1041014","CE_DA":"1051218","CO_TI":"依交維計畫訂定時間施工日間施工9時30分至16時","TC_MA":"陳建志","TC_TL":"0917891196","TC_MA3":"王明聖","TC_TL3":"0936055412","NPURP":"市政建設","DTYPE":null},{"_id":"3","AC_NO":"104009471","ST_NO":"1","SNO":"10","APPMODE":"0","X":"301353.678","Y":"2773257.727","APPTIME":"1051020093258","APP_NAME":"衛工處","C_NAME":"大同","ADDR":"環河北路2段123巷附近地區","CB_DA":"1041202","CE_DA":"1051031","CO_TI":"日間施工9時30分至16時","TC_MA":"林懋孝","TC_TL":"0963568235","TC_MA3":"黃岱成","TC_TL3":"0981143142","NPURP":"市政建設","DTYPE":null},{"_id":"4","AC_NO":"105001030-3","ST_NO":"1","SNO":"1","APPMODE":"0","X":"301414.538","Y":"2775896.624","APPTIME":"1051020090853","APP_NAME":"自來水北區","C_NAME":"士林","ADDR":"社子里社中街148號前","CB_DA":"1051019","CE_DA":"1051021","CO_TI":"日間施工9時30分至16時","TC_MA":"王中平","TC_TL":"0909232896","TC_MA3":"張睿承","TC_TL3":"0932188924","NPURP":"管線單位需求-配合拆遷","DTYPE":null},{"_id":"5","AC_NO":"105001797","ST_NO":"1","SNO":"152","APPMODE":"0","X":"310236.838","Y":"2772792.701","APPTIME":"1051020092353","APP_NAME":"衛工處","C_NAME":"內湖","ADDR":"安康路（安康路93巷至安美街）","CB_DA":"1050323","CE_DA":"1051111","CO_TI":"依交維計畫訂定時間施工巷弄道路週休二日不得施工 日間施工9時30分至16時","TC_MA":"孔德輝","TC_TL":"0978121275","TC_MA3":"洪基富","TC_TL3":"0913165905","NPURP":"市政建設","DTYPE":null},{"_id":"6","AC_NO":"105003354-1","ST_NO":"1","SNO":"8","APPMODE":"0","X":"300335.865","Y":"2770379.828","APPTIME":"1051020094654","APP_NAME":"自來水工總","C_NAME":"萬華","ADDR":"西園路1段34巷(西園路至環河南路)","CB_DA":"1051004","CE_DA":"1051030","CO_TI":"日間施工9時30分至16時 巷弄道路周休二日不得施工","TC_MA":"周采青","TC_TL":"0978331586","TC_MA3":"邱奕祺","TC_TL3":"0983130045","NPURP":"市政建設","DTYPE":null},{"_id":"7","AC_NO":"1050038874","ST_NO":"0","SNO":"4","APPMODE":"6","X":"308136.292","Y":"2773124.326","APPTIME":"1051020093245","APP_NAME":"新台北有線","C_NAME":"內湖","ADDR":"民權東路6段11巷及舊宗路1、2段，新湖二路口、新湖三路口","CB_DA":"1051018","CE_DA":"1051022","CO_TI":"09:30-16:00","TC_MA":"蔡益鑫","TC_TL":"R120298912","TC_MA3":"郭金富","TC_TL3":"0956283339","NPURP":"人手孔施工","DTYPE":null},{"_id":"8","AC_NO":"1050040438","ST_NO":"0","SNO":"5","APPMODE":"6","X":"300020.725","Y":"2769937.152","APPTIME":"1051020104848","APP_NAME":"台灣智慧光網","C_NAME":"萬華","ADDR":"環河南路1段2段.3段.廣州街.和平西路1.2.3段.桂林路(包含巷弄)","CB_DA":"1051017","CE_DA":"1051021","CO_TI":"09:30-16:00","TC_MA":"陳瑋叡","TC_TL":"0973052585","TC_MA3":"蔡盛博","TC_TL3":"0955599993","NPURP":"人手孔施工","DTYPE":null},{"_id":"9","AC_NO":"1050040788","ST_NO":"0","SNO":"2","APPMODE":"6","X":"299969.105","Y":"2768564.013","APPTIME":"1051020120044","APP_NAME":"台電市區","C_NAME":"萬華","ADDR":"寶興街149-1號.159號","CB_DA":"1051017","CE_DA":"1051031","CO_TI":"09:30-16:00","TC_MA":"曾木鑾","TC_TL":"U120461383","TC_MA3":"林智賢","TC_TL3":"0905060835","NPURP":"人手孔施工","DTYPE":null},{"_id":"10","AC_NO":"1050040887","ST_NO":"0","SNO":"1","APPMODE":"6","X":"300504.229","Y":"2770594.672","APPTIME":"1051020105309","APP_NAME":"台灣智慧光網","C_NAME":"萬華","ADDR":"西昌街和昆明街和永福街和環河南路1段和雅江街和長沙街2段和貴陽街2段柳州街和西寧南路{含巷弄沿線}","CB_DA":"1051020","CE_DA":"1051024","CO_TI":"09:30-16:00","TC_MA":"謝志誠","TC_TL":"0933649016","TC_MA3":"李旻翰","TC_TL3":"0921923491","NPURP":"人手孔施工","DTYPE":null},{"_id":"11","AC_NO":"1050040989","ST_NO":"0","SNO":"1","APPMODE":"6","X":"301476.913","Y":"2775820.586","APPTIME":"1051020104808","APP_NAME":"電信士林","C_NAME":"士林","ADDR":"社中街116號前","CB_DA":"1051015","CE_DA":"1051029","CO_TI":"09:30-16:00","TC_MA":"王芬滄","TC_TL":"0937026747","TC_MA3":"陳威龍","TC_TL3":"0913125552","NPURP":"人手孔施工","DTYPE":null},{"_id":"12","AC_NO":"1050041176","ST_NO":"0","SNO":"3","APPMODE":"6","X":"302292.681","Y":"2771903.281","APPTIME":"1051020110551","APP_NAME":"台灣智慧光網","C_NAME":"大同","ADDR":"承德路2段、南京西路、民生西路、赤峰街(以上皆含巷弄)","CB_DA":"1051017","CE_DA":"1051021","CO_TI":"09:30-16:00","TC_MA":"許永富","TC_TL":"0955888266","TC_MA3":"馬宇文","TC_TL3":"0966-560-273","NPURP":"人手孔施工","DTYPE":null},{"_id":"13","AC_NO":"1050041457","ST_NO":"0","SNO":"2","APPMODE":"6","X":"302216.136","Y":"2776230.448","APPTIME":"1051020092301","APP_NAME":"台灣智慧光網","C_NAME":"士林","ADDR":"士商路.承德路5段.通河東街.中正路(以上皆含巷弄)","CB_DA":"1051018","CE_DA":"1051022","CO_TI":"09:30-16:00","TC_MA":"許永富","TC_TL":"0955888266","TC_MA3":"陳金龍","TC_TL3":"0955-898-681","NPURP":"人手孔施工","DTYPE":null},{"_id":"14","AC_NO":"1050041686","ST_NO":"0","SNO":"1","APPMODE":"6","X":"310013.688","Y":"2771446.118","APPTIME":"1051020102928","APP_NAME":"水利處","C_NAME":"南港","ADDR":"昆陽157巷23號,忠孝東路6段462巷口","CB_DA":"1051020","CE_DA":"1051103","CO_TI":"09:30-16:00","TC_MA":"游明智","TC_TL":"0915888891","TC_MA3":"郭保忠","TC_TL3":"0980730557","NPURP":"人手孔施工","DTYPE":null},{"_id":"15","AC_NO":"1050041707","ST_NO":"0","SNO":"1","APPMODE":"6","X":"301994.853","Y":"2771523.193","APPTIME":"1051020110825","APP_NAME":"台灣智慧光網","C_NAME":"大同","ADDR":"承德路1段、2段、長安西路、太原路、華陰街、平陽街(以上皆含巷弄)","CB_DA":"1051019","CE_DA":"1051023","CO_TI":"09:30-16:00","TC_MA":"許永富","TC_TL":"0955888266","TC_MA3":"李文傑","TC_TL3":"0966-066-199","NPURP":"人手孔施工","DTYPE":null},{"_id":"16","AC_NO":"1050041711","ST_NO":"0","SNO":"1","APPMODE":"6","X":"303907.371","Y":"2770389.201","APPTIME":"1051020113129","APP_NAME":"台電市區","C_NAME":"大安","ADDR":"新生南路1段103巷11號","CB_DA":"1051020","CE_DA":"1051031","CO_TI":"09:30-16:00","TC_MA":"曾木鑾","TC_TL":"U120461383","TC_MA3":"蔡榮輝","TC_TL3":"0980201117","NPURP":"人手孔施工","DTYPE":null},{"_id":"17","AC_NO":"1050041725","ST_NO":"0","SNO":"1","APPMODE":"6","X":"301929.571","Y":"2776253.626","APPTIME":"1051020114709","APP_NAME":"台灣國際纜網","C_NAME":"士林","ADDR":"承德路5段78號前","CB_DA":"1051020","CE_DA":"1051028","CO_TI":"09:30-16:00","TC_MA":"陳義昌","TC_TL":"0987580307","TC_MA3":"潘亞榮","TC_TL3":"0985115806","NPURP":"人手孔施工","DTYPE":null},{"_id":"18","AC_NO":"1050041731","ST_NO":"0","SNO":"1","APPMODE":"6","X":"300997.01","Y":"2779743.269","APPTIME":"1051020103752","APP_NAME":"陽明山有線","C_NAME":"北投","ADDR":"公館路及三合街一段全線(單雙)號含巷弄啟閉作業!","CB_DA":"1051020","CE_DA":"1051024","CO_TI":"09:30-16:00","TC_MA":"陳銘慶","TC_TL":"0932087480","TC_MA3":"彭文彬","TC_TL3":"0912315553","NPURP":"人手孔施工","DTYPE":null},{"_id":"19","AC_NO":"1050041790","ST_NO":"0","SNO":"1","APPMODE":"6","X":"306328.894","Y":"2772775.836","APPTIME":"1051020104254","APP_NAME":"台電市區","C_NAME":"松山","ADDR":"民權東路4段民權公園旁.停車場入口旁.網球場外面停車場入口旁","CB_DA":"1051020","CE_DA":"1051022","CO_TI":"09:30-16:00","TC_MA":"施政成","TC_TL":"0987878561","TC_MA3":"陳盈志","TC_TL3":"0930220095","NPURP":"人手孔施工","DTYPE":null},{"_id":"20","AC_NO":"1050041866","ST_NO":"0","SNO":"1","APPMODE":"6","X":"300365.239","Y":"2769328.997","APPTIME":"1051020094549","APP_NAME":"台灣智慧光網","C_NAME":"萬華","ADDR":"西寧南路、開封街二段 、莒光路(以上皆含本線巷弄)","CB_DA":"1051020","CE_DA":"1051024","CO_TI":"09:30-16:00","TC_MA":"練怡孝","TC_TL":"0985453955","TC_MA3":"林昆毅","TC_TL3":"0912924268","NPURP":"人手孔施工","DTYPE":null},{"_id":"21","AC_NO":"1050041957","ST_NO":"0","SNO":"1","APPMODE":"6","X":"307107.46","Y":"2764036.463","APPTIME":"1051020095437","APP_NAME":"亞太電信","C_NAME":"文山","ADDR":"木新路3段與保儀路本線及周邊沿線巷弄","CB_DA":"1051020","CE_DA":"1051022","CO_TI":"09:30-16:00","TC_MA":"李俊奇","TC_TL":"李俊奇","TC_MA3":"李安鎮","TC_TL3":"0963431192","NPURP":"人手孔施工","DTYPE":null},{"_id":"22","AC_NO":"105004286","ST_NO":"1","SNO":"4","APPMODE":"0","X":"302724.71","Y":"2775234.855","APPTIME":"1051020093835","APP_NAME":"衛工處","C_NAME":"士林","ADDR":"後港街45巷1號前","CB_DA":"1050704","CE_DA":"1051021","CO_TI":"日間施工9時至16時30分","TC_MA":"黃步賢","TC_TL":"0939758534","TC_MA3":"廖英佐","TC_TL3":"0980045137","NPURP":"市政建設","DTYPE":null},{"_id":"23","AC_NO":"105004837","ST_NO":"1","SNO":"1","APPMODE":"0","X":"304618.338","Y":"2771077.623","APPTIME":"1051020092437","APP_NAME":"台電市區","C_NAME":"中山","ADDR":"八德路2段260號至274號前","CB_DA":"1050727","CE_DA":"1051021","CO_TI":"日間施工9時30分至16時","TC_MA":"麥家閩","TC_TL":"23788111","TC_MA3":"許明順","TC_TL3":"0953208360","NPURP":"市政建設","DTYPE":null},{"_id":"24","AC_NO":"105005525","ST_NO":"1","SNO":"17","APPMODE":"0","X":"307925.541","Y":"2770290.088","APPTIME":"1051020095505","APP_NAME":"水利處","C_NAME":"信義","ADDR":"忠孝東路5段372巷27弄2號至58號前","CB_DA":"1050901","CE_DA":"1051030","CO_TI":"日間施工9時30分至16時，巷道周休2日停止施工。","TC_MA":"游明智","TC_TL":"0915888891","TC_MA3":"毛坤龍","TC_TL3":"0973130238","NPURP":"市政建設","DTYPE":null},{"_id":"25","AC_NO":"10500570","ST_NO":"0","SNO":"42","APPMODE":"5","X":"300000.35","Y":"2767656.561","APPTIME":"1051020081803","APP_NAME":"新工處","C_NAME":"萬華","ADDR":"華中橋","CB_DA":"1050427","CE_DA":"1060415","CO_TI":null,"TC_MA":"黃詩銘","TC_TL":"0937953862","TC_MA3":"劉炳村","TC_TL3":"0985990646","NPURP":"道路維護施工","DTYPE":null},{"_id":"26","AC_NO":"105005712","ST_NO":"1","SNO":"24","APPMODE":"0","X":"305455.807","Y":"2766283.197","APPTIME":"1051020100452","APP_NAME":"水利處","C_NAME":"文山","ADDR":"福興路63巷","CB_DA":"1050901","CE_DA":"1060428","CO_TI":"日間施工9時至16時，巷弄道路週休二日不得施工","TC_MA":"陳奕先","TC_TL":"0955150837","TC_MA3":"蘇國榮","TC_TL3":"0986689897","NPURP":"新設","DTYPE":"施工遇管障"},{"_id":"27","AC_NO":"105005746","ST_NO":"1","SNO":"31","APPMODE":"0","X":"305440.383","Y":"2782500.81","APPTIME":"1051020093941","APP_NAME":"衛工處","C_NAME":"士林","ADDR":"湖山路1段以南，紗帽路以東，和平路以北，陽明路1段以西","CB_DA":"1050829","CE_DA":"1071211","CO_TI":"日間施工9時30分至16時","TC_MA":"梁傑中","TC_TL":"0928590686","TC_MA3":"沈建緯","TC_TL3":"0926926145","NPURP":"市政建設","DTYPE":null},{"_id":"28","AC_NO":"105005780-2","ST_NO":"1","SNO":"2","APPMODE":"0","X":"304601.009","Y":"2765452.835","APPTIME":"1051020111525","APP_NAME":"台電南區","C_NAME":"文山","ADDR":"羅斯福路6段142巷內","CB_DA":"1050926","CE_DA":"1051021","CO_TI":"日間施工9時30分至16時","TC_MA":"李曉萍","TC_TL":"0935977683","TC_MA3":"丁尉哲","TC_TL3":"0935230119","NPURP":"民生需求-新建房屋","DTYPE":null},{"_id":"29","AC_NO":"105005958","ST_NO":"1","SNO":"25","APPMODE":"0","X":"300347.736","Y":"2777730.973","APPTIME":"1051020093111","APP_NAME":"水利處","C_NAME":"北投","ADDR":"洲美街271號(北投焚化廠停車場至焚化爐出入口)","CB_DA":"1050912","CE_DA":"1051119","CO_TI":"日間施工9時30分至16時","TC_MA":"許崇銘","TC_TL":"0987763539","TC_MA3":"林文宗","TC_TL3":"0937209251","NPURP":"市政建設","DTYPE":null},{"_id":"30","AC_NO":"105006009","ST_NO":"1","SNO":"11","APPMODE":"0","X":"305159.939","Y":"2766098.72","APPTIME":"1051020095350","APP_NAME":"衛工處","C_NAME":"文山","ADDR":"景豐街48巷11弄16號至48號前","CB_DA":"1050908","CE_DA":"1051111","CO_TI":"日間施工9時至16時，巷弄道路週休二日不得施工","TC_MA":"蔡文軒","TC_TL":"0917222255","TC_MA3":"林詩寰","TC_TL3":"0982629911","NPURP":"市政建設","DTYPE":null},{"_id":"31","AC_NO":"105006067","ST_NO":"1","SNO":"20","APPMODE":"0","X":"307829.966","Y":"2774994.734","APPTIME":"1051020085214","APP_NAME":"水利處","C_NAME":"內湖","ADDR":"麗山街348巷8號前至內湖路1段629巷口及麗山街348巷至港華街口","CB_DA":"1050913","CE_DA":"1060205","CO_TI":"依交維計畫訂定時間施工  日間施工9時30分至16時  巷弄道路週休二日不得施工 禁止道路施工時間詳公告","TC_MA":"許育誠","TC_TL":"0911008479","TC_MA3":"陳宏斌","TC_TL3":"0903034459","NPURP":"市政建設","DTYPE":null},{"_id":"32","AC_NO":"105006087","ST_NO":"1","SNO":"1","APPMODE":"0","X":"305554.677","Y":"2770156.722","APPTIME":"1051020091208","APP_NAME":"水利處","C_NAME":"大安","ADDR":"仁愛路4段105巷8號","CB_DA":"1051019","CE_DA":"1051202","CO_TI":"日間施工9時至16時，巷弄道路週休二日不得施工","TC_MA":"陳屏甄","TC_TL":"0980909277","TC_MA3":"黃柏勝","TC_TL3":"0912875122","NPURP":"市政建設","DTYPE":null},{"_id":"33","AC_NO":"105006143","ST_NO":"1","SNO":"2","APPMODE":"0","X":"309906.39","Y":"2773624.335","APPTIME":"1051020093114","APP_NAME":"衛工處","C_NAME":"內湖","ADDR":"民權東路6段123巷21弄18號至46號","CB_DA":"1051012","CE_DA":"1051021","CO_TI":"日間施工9時30分至16時  巷弄道路週休二日不得施工","TC_MA":"邱啟禎","TC_TL":"0988383145","TC_MA3":"梁亦宏","TC_TL3":"0989438087","NPURP":"市政建設","DTYPE":null},{"_id":"34","AC_NO":"105006167-2","ST_NO":"1","SNO":"6","APPMODE":"0","X":"300909.562","Y":"2770884.288","APPTIME":"1051020093929","APP_NAME":"大台北瓦斯","C_NAME":"萬華","ADDR":"武昌街2段(昆明街口至武昌街2段118號前)","CB_DA":"1051003","CE_DA":"1051024","CO_TI":"日間施工9時30分至16時 夜間施工23時至5時30分","TC_MA":"朱振宇","TC_TL":"0911929950","TC_MA3":"莊正輝","TC_TL3":"0931324950","NPURP":"管線單位需求-既設管線改善","DTYPE":null},{"_id":"35","AC_NO":"105006245-1","ST_NO":"1","SNO":"3","APPMODE":"0","X":"303977.311","Y":"2769620.386","APPTIME":"1051020090836","APP_NAME":"電信南區","C_NAME":"大安","ADDR":"信義路3段33號至41-2號人行道","CB_DA":"1050926","CE_DA":"1051020","CO_TI":"日間施工9時30分至16時","TC_MA":"王乘運","TC_TL":"0928230074","TC_MA3":"陳榮川","TC_TL3":"0963715879","NPURP":"民生需求-新建房屋","DTYPE":null},{"_id":"36","AC_NO":"105006248","ST_NO":"1","SNO":"6","APPMODE":"0","X":"302227.838","Y":"2775833.365","APPTIME":"1051020093755","APP_NAME":"公園處","C_NAME":"士林","ADDR":"承德路4段307至309號前及338號至332號旁及294號至308號前人行道與福港街32號前及大南路428巷口","CB_DA":"1051012","CE_DA":"1051112","CO_TI":"日間施工9時30分至16時","TC_MA":"洪允錐","TC_TL":"25928650","TC_MA3":"沈勝乾","TC_TL3":"0980952751","NPURP":"市政建設","DTYPE":null},{"_id":"37","AC_NO":"105006267","ST_NO":"1","SNO":"17","APPMODE":"0","X":"302537.94","Y":"2768825.599","APPTIME":"1051020093020","APP_NAME":"衛工處","C_NAME":"中正","ADDR":"和平西路1段20至46號","CB_DA":"1050922","CE_DA":"1051115","CO_TI":"日間施工9時30分至16時","TC_MA":"施議樵","TC_TL":"0935949892","TC_MA3":"吳承運","TC_TL3":"0919295660","NPURP":"市政建設","DTYPE":null},{"_id":"38","AC_NO":"105006315","ST_NO":"1","SNO":"4","APPMODE":"0","X":"303762.509","Y":"2776810.603","APPTIME":"1051020090240","APP_NAME":"自來水陽明","C_NAME":"士林","ADDR":"雨農路60巷口至忠勇街40巷一帶","CB_DA":"1051011","CE_DA":"1051030","CO_TI":"日間施工9時30分至16時","TC_MA":"黃兆均","TC_TL":"0921460528","TC_MA3":"李俊傑","TC_TL3":"0975755672","NPURP":"管線單位需求-既設管線改善","DTYPE":null},{"_id":"39","AC_NO":"105006327","ST_NO":"1","SNO":"2","APPMODE":"0","X":"306297.094","Y":"2771008.644","APPTIME":"1051020092338","APP_NAME":"自來水南區","C_NAME":"松山","ADDR":"光復南路45巷2號旁至28號旁及八德路4段36巷(光復南路45巷至光復南路57巷)","CB_DA":"1051003","CE_DA":"1051102","CO_TI":"日間施工9時30分至16時，周休2日停止施工，10月10日國慶日禁挖。","TC_MA":"陳信良","TC_TL":"0979213265","TC_MA3":"張定璿","TC_TL3":"0922094979","NPURP":"市政建設","DTYPE":null},{"_id":"40","AC_NO":"105006346-1","ST_NO":"1","SNO":"4","APPMODE":"0","X":"305885.553","Y":"2771234.94","APPTIME":"1051020091628","APP_NAME":"台電市區","C_NAME":"松山","ADDR":"八德路3段111號前至182號前","CB_DA":"1051017","CE_DA":"1051031","CO_TI":"日間施工9時30分至16時30分","TC_MA":"雷鳴","TC_TL":"23788111","TC_MA3":"陳聰輝","TC_TL3":"0953208377","NPURP":"管線單位需求-建設需求","DTYPE":null},{"_id":"41","AC_NO":"105006396","ST_NO":"1","SNO":"1","APPMODE":"0","X":"303626.268","Y":"2768617.282","APPTIME":"1051020085556","APP_NAME":"自來水南區","C_NAME":"大安","ADDR":"泰順街38巷(泰順街至龍泉街),泰順街40巷1號旁","CB_DA":"1051017","CE_DA":"1051118","CO_TI":"日間施工9時至16時，巷弄道路週休二日不得施工","TC_MA":"王耀霖","TC_TL":"0979213263","TC_MA3":"蕭國浩","TC_TL3":"0922800558","NPURP":"市政建設","DTYPE":null},{"_id":"42","AC_NO":"105006438","ST_NO":"1","SNO":"4","APPMODE":"0","X":"300441.055","Y":"2768684.189","APPTIME":"1051020092357","APP_NAME":"自來水東區","C_NAME":"萬華","ADDR":"民和街18號至126號、東園街73巷14號至38號及40弄口、萬大路322及344巷、德昌街口至5號","CB_DA":"1051005","CE_DA":"1051216","CO_TI":"日間施工9時30分至16時，巷弄道路周休二日不得施工","TC_MA":"蔡裕國","TC_TL":"0955625575","TC_MA3":"張玉興","TC_TL3":"0988321936","NPURP":"市政建設","DTYPE":null},{"_id":"43","AC_NO":"105006444","ST_NO":"1","SNO":"7","APPMODE":"0","X":"299324.645","Y":"2781723.414","APPTIME":"1051020084431","APP_NAME":"衛工處","C_NAME":"北投","ADDR":"稻香路150巷全巷","CB_DA":"1051003","CE_DA":"1051031","CO_TI":"日間施工9時30分至16時","TC_MA":"許芬妮","TC_TL":"0919761228","TC_MA3":"黃國強","TC_TL3":"0985916991","NPURP":"市政建設","DTYPE":null},{"_id":"44","AC_NO":"105006447","ST_NO":"1","SNO":"5","APPMODE":"0","X":"304805.025","Y":"2771506.061","APPTIME":"1051020085520","APP_NAME":"大台北瓦斯","C_NAME":"中山","ADDR":"遼寧街93號前至遼寧街101巷31號前","CB_DA":"1051005","CE_DA":"1051114","CO_TI":"日間施工9時30分至16時","TC_MA":"蔡明翰","TC_TL":"0961330489","TC_MA3":"王永慶","TC_TL3":"0910091325","NPURP":"管線單位需求-既設管線改善","DTYPE":null},{"_id":"45","AC_NO":"105006472-3","ST_NO":"1","SNO":"2","APPMODE":"0","X":"309799.861","Y":"2773258.732","APPTIME":"1051020094559","APP_NAME":"隆雲股份有限公司","C_NAME":"內湖","ADDR":"民權東路6段180巷77弄口","CB_DA":"1051019","CE_DA":"1051021","CO_TI":"日間施工9時30分至16時","TC_MA":"馬仲伶","TC_TL":"0937195158","TC_MA3":"許原寶","TC_TL3":"0927767378","NPURP":"民生需求-新建房屋","DTYPE":null},{"_id":"46","AC_NO":"105006501","ST_NO":"1","SNO":"1","APPMODE":"0","X":"309501.196","Y":"2771274.842","APPTIME":"1051020100746","APP_NAME":"電信東區","C_NAME":"南港","ADDR":"忠孝東路6段278巷23弄1號附近","CB_DA":"1051020","CE_DA":"1051021","CO_TI":"日間施工9時30分至16時   單方向可留設3.5公尺以上空間通行","TC_MA":"紀弘亮51119-3560325","TC_TL":"0910380815","TC_MA3":"潘宿結","TC_TL3":"0988661267","NPURP":"民生需求-舊有用戶","DTYPE":null},{"_id":"47","AC_NO":"105006510","ST_NO":"1","SNO":"4","APPMODE":"0","X":"306195.567","Y":"2768032.144","APPTIME":"1051020091642","APP_NAME":"電信南區","C_NAME":"大安","ADDR":"富陽街101號至123號、157巷3號至13號、163巷口、和平東路3段332號至340號人行道、3段346巷7號旁及21號、臥龍街252號至256-1號人行道","CB_DA":"1051017","CE_DA":"1051021","CO_TI":"日間施工9時30分至16時","TC_MA":"王乘運","TC_TL":"0928230074","TC_MA3":"林堂春","TC_TL3":"0939901831","NPURP":"管線單位需求-既設管線改善","DTYPE":null},{"_id":"48","AC_NO":"105006540-1","ST_NO":"1","SNO":"3","APPMODE":"0","X":"301521.83","Y":"2771133.908","APPTIME":"1051020094626","APP_NAME":"台電市區","C_NAME":"中正","ADDR":"中華路1段5號前","CB_DA":"1051017","CE_DA":"1051021","CO_TI":"日間施工9時30分至16時","TC_MA":"周漢樟","TC_TL":"0937841988","TC_MA3":"謝佳良","TC_TL3":"0978721677","NPURP":"民生需求-新建房屋","DTYPE":null},{"_id":"49","AC_NO":"105006545-2","ST_NO":"1","SNO":"1","APPMODE":"0","X":"301723.613","Y":"2778117.182","APPTIME":"1051020092904","APP_NAME":"陽明山瓦斯","C_NAME":"北投","ADDR":"自強街31巷6號旁附近(福興里)","CB_DA":"1051019","CE_DA":"1051021","CO_TI":"日間施工9時30分至16時","TC_MA":"陳柏翰","TC_TL":"0933125020","TC_MA3":"洪文灝","TC_TL3":"0933801960","NPURP":"民生需求-新建房屋","DTYPE":null},{"_id":"50","AC_NO":"105006594","ST_NO":"1","SNO":"1","APPMODE":"0","X":"308054.451","Y":"2770474.598","APPTIME":"1051020093013","APP_NAME":"麗冠有線","C_NAME":"信義","ADDR":"忠孝東路5段423巷3弄1號側、忠孝東路5段295巷6弄33號前","CB_DA":"1051017","CE_DA":"1051021","CO_TI":"日間施工9時30分至16時","TC_MA":"張皓強","TC_TL":"0920656179","TC_MA3":"林威助","TC_TL3":"0988707608","NPURP":"14","DTYPE":null},{"_id":"51","AC_NO":"105006725","ST_NO":"1","SNO":"1","APPMODE":"0","X":"305348.075","Y":"2780970.535","APPTIME":"1051020094943","APP_NAME":"電信士林","C_NAME":"士林","ADDR":"建業路34之2號~36巷8弄口","CB_DA":"1051019","CE_DA":"1051021","CO_TI":"日間施工9時30分至16時","TC_MA":"王芬滄","TC_TL":"0937026747","TC_MA3":"李賢德","TC_TL3":"0929858518","NPURP":"民生需求-新建房屋","DTYPE":null},{"_id":"52","AC_NO":"105006729-4","ST_NO":"1","SNO":"2","APPMODE":"0","X":"307617.206","Y":"2769002.069","APPTIME":"1051020094539","APP_NAME":"大台北瓦斯","C_NAME":"信義","ADDR":"信義路5段150巷8號前向東約24公尺","CB_DA":"1051019","CE_DA":"1051021","CO_TI":"日間施工9時至16時30分","TC_MA":"曹博順","TC_TL":"0933064136","TC_MA3":"陳仕榮","TC_TL3":"0936664588","NPURP":"民生需求-新建房屋","DTYPE":null},{"_id":"53","AC_NO":"105006737","ST_NO":"1","SNO":"1","APPMODE":"0","X":"300733.853","Y":"2775766.492","APPTIME":"1051020090956","APP_NAME":"公園處","C_NAME":"士林","ADDR":"延平北路6段308號前迴轉道及延平北路6段146號前等2處","CB_DA":"1051018","CE_DA":"1051022","CO_TI":"日間施工9時30分至16時","TC_MA":"洪允錐","TC_TL":"25928650","TC_MA3":"張偉郁","TC_TL3":"0914155158","NPURP":"市政建設","DTYPE":null},{"_id":"54","AC_NO":"105006767","ST_NO":"1","SNO":"4","APPMODE":"0","X":"308392.665","Y":"2773472.83","APPTIME":"1051020092633","APP_NAME":"麗冠有線","C_NAME":"內湖","ADDR":"民權東路6段58號側至民權東路6段50號旁(中油前)及民權東路6段38號至民權東路6段15巷37號一帶","CB_DA":"1051015","CE_DA":"1051025","CO_TI":"依交維計畫訂定時間施工  日間施工9時30分至16時","TC_MA":"陳瑞宗","TC_TL":"0988919811","TC_MA3":"洪仁森","TC_TL3":"0932877256","NPURP":"管線單位需求-建設需求","DTYPE":null},{"_id":"55","AC_NO":"105006770-1","ST_NO":"1","SNO":"1","APPMODE":"0","X":"304115.571","Y":"2768684.993","APPTIME":"1051020100510","APP_NAME":"電信南區","C_NAME":"大安","ADDR":"新生南路3段11巷8號至11號旁","CB_DA":"1051019","CE_DA":"1051021","CO_TI":"日間施工9時30分至16時","TC_MA":"王乘運","TC_TL":"0928230074","TC_MA3":"陳建嘉","TC_TL3":"0986159328","NPURP":"民生需求-新建房屋","DTYPE":null},{"_id":"68","AC_NO":"10502454","ST_NO":"0","SNO":"4","APPMODE":"5","X":"308288.826","Y":"2770913.254","APPTIME":"1051020093309","APP_NAME":"新工處","C_NAME":"信義","ADDR":"松山路(永吉路至忠孝東路5段)","CB_DA":"1051014","CE_DA":"1051024","CO_TI":null,"TC_MA":"黃笙瑋","TC_TL":"0986606775","TC_MA3":"闕詩芸","TC_TL3":"0912098677","NPURP":"道路維護施工","DTYPE":null},{"_id":"56","AC_NO":"105006771","ST_NO":"1","SNO":"1","APPMODE":"0","X":"300859.297","Y":"2770764.85","APPTIME":"1051020093044","APP_NAME":"台電市區","C_NAME":"萬華","ADDR":"峨嵋街60號-82號前","CB_DA":"1051019","CE_DA":"1051021","CO_TI":"日間施工9時30分至16時","TC_MA":"鍾台珠","TC_TL":"0937077795","TC_MA3":"吳添財","TC_TL3":"0918923998","NPURP":"民生需求-舊有用戶","DTYPE":null},{"_id":"57","AC_NO":"105006799","ST_NO":"1","SNO":"1","APPMODE":"0","X":"299979.009","Y":"2767746.099","APPTIME":"1051020093713","APP_NAME":"自來水西區","C_NAME":"萬華","ADDR":"環河南路3段369號旁(華中里)","CB_DA":"1051019","CE_DA":"1051020","CO_TI":"日間施工9時30分至16時","TC_MA":"柳昱丞","TC_TL":"0979213272","TC_MA3":"劉國樑","TC_TL3":"0933833599","NPURP":"民生需求-舊有用戶","DTYPE":null},{"_id":"58","AC_NO":"105006831","ST_NO":"1","SNO":"1","APPMODE":"0","X":"301070.186","Y":"2770707.167","APPTIME":"1051020095009","APP_NAME":"水利處","C_NAME":"萬華","ADDR":"西寧南路與峨嵋街西南角","CB_DA":"1051019","CE_DA":"1051107","CO_TI":"日間施工9時30分至16時","TC_MA":"陳屏甄","TC_TL":"0980909277","TC_MA3":"鄭子敬","TC_TL3":"0930995658","NPURP":"市政建設","DTYPE":null},{"_id":"59","AC_NO":"10500827","ST_NO":"0","SNO":"1","APPMODE":"5","X":"301233.87","Y":"2771259.862","APPTIME":"1050524100648","APP_NAME":"新工處","C_NAME":"萬華","ADDR":"忠孝西路自環河南路至重慶南路","CB_DA":"1050524","CE_DA":"1051130","CO_TI":null,"TC_MA":"陳嘉隆","TC_TL":"0913350298","TC_MA3":"蘇國華","TC_TL3":"0935779289","NPURP":"道路維護施工","DTYPE":null},{"_id":"60","AC_NO":"10500833","ST_NO":"0","SNO":"254","APPMODE":"5","X":"301525.972","Y":"2775502.424","APPTIME":"1051020095922","APP_NAME":"新工處","C_NAME":"士林","ADDR":"一般橋梁-重陽橋引道","CB_DA":"1050524","CE_DA":"1060128","CO_TI":null,"TC_MA":"尹鳳農","TC_TL":"0918969189","TC_MA3":"吳佳達","TC_TL3":"0966552560","NPURP":"道路維護施工","DTYPE":null},{"_id":"61","AC_NO":"10501407","ST_NO":"0","SNO":"21","APPMODE":"5","X":"300736.676","Y":"2780898.494","APPTIME":"1051020104220","APP_NAME":"新工處","C_NAME":"北投","ADDR":"北投區光明路(自132號至218號)前人行道","CB_DA":"1050925","CE_DA":"1051105","CO_TI":null,"TC_MA":"陳鴻仁","TC_TL":"0986281770","TC_MA3":"吳廷文","TC_TL3":"0928242759","NPURP":"道路維護施工","DTYPE":null},{"_id":"62","AC_NO":"10501913","ST_NO":"0","SNO":"22","APPMODE":"5","X":"301888.137","Y":"2773956.17","APPTIME":"1051020080413","APP_NAME":"新工處","C_NAME":"大同","ADDR":"105年度大同區哈密街（85至115號）地磚更新工程","CB_DA":"1050901","CE_DA":"1051030","CO_TI":null,"TC_MA":"林政南","TC_TL":"0953161521","TC_MA3":"陳義元","TC_TL3":"0920008515","NPURP":"道路維護施工","DTYPE":null},{"_id":"63","AC_NO":"10502087","ST_NO":"0","SNO":"34","APPMODE":"5","X":"304535.159","Y":"2771118.965","APPTIME":"1051020084622","APP_NAME":"新工處","C_NAME":"中山","ADDR":"龍江路自八德路2段至長安東路2段間單號側人行道鋪面更新、中山北路2段77-2及95號鋪面積水改善工程","CB_DA":"1050907","CE_DA":"1051120","CO_TI":null,"TC_MA":"許崇榮","TC_TL":"0982688337","TC_MA3":"李守華","TC_TL3":"0955324973","NPURP":"道路維護施工","DTYPE":null},{"_id":"64","AC_NO":"10502281","ST_NO":"0","SNO":"11","APPMODE":"5","X":"302580.771","Y":"2772665.819","APPTIME":"1051020082156","APP_NAME":"新工處","C_NAME":"中山","ADDR":"天祥路自民權西路至錦西街間兩側人行道鋪面更新工程(第7通報單)","CB_DA":"1050927","CE_DA":"1051215","CO_TI":null,"TC_MA":"許崇榮","TC_TL":"0982688337","TC_MA3":"李守華","TC_TL3":"0955324973","NPURP":"道路維護施工","DTYPE":null},{"_id":"65","AC_NO":"10502301","ST_NO":"0","SNO":"15","APPMODE":"5","X":"306050.195","Y":"2772128.612","APPTIME":"1051020090517","APP_NAME":"新工處","C_NAME":"松山","ADDR":"第2次通報單-光復北路232號、民生東路130號、新東街12巷、撫遠街187號、敦化北路201巷、虎林街9號、八德路四段259號、民權東路三段136號等無遮簷人行道及騎樓整平","CB_DA":"1050929","CE_DA":"1051206","CO_TI":null,"TC_MA":"蔡欣汎","TC_TL":"0919522513","TC_MA3":"楊崇德","TC_TL3":"0932221982","NPURP":"道路維護施工","DTYPE":null},{"_id":"66","AC_NO":"10502434","ST_NO":"0","SNO":"5","APPMODE":"5","X":"301833.134","Y":"2774620.552","APPTIME":"1051020091604","APP_NAME":"新工處","C_NAME":"大同","ADDR":"105年度大同區重慶北路４段２號（士林簡易庭）前至交流道橋下中央分隔島緣石更新工程","CB_DA":"1051012","CE_DA":"1051116","CO_TI":null,"TC_MA":"許崇榮","TC_TL":"0982688337","TC_MA3":"王祖銓","TC_TL3":"0910196038","NPURP":"道路維護施工","DTYPE":null},{"_id":"67","AC_NO":"10502441","ST_NO":"0","SNO":"3","APPMODE":"5","X":"306877.625","Y":"2770617.598","APPTIME":"1051020075926","APP_NAME":"新工處","C_NAME":"信義","ADDR":"忠孝東路四段553巷16弄\r\n林口街80巷","CB_DA":"1051014","CE_DA":"1051219","CO_TI":null,"TC_MA":"黃觀林","TC_TL":"0980224132","TC_MA3":"李守華","TC_TL3":"0955324973","NPURP":"道路維護施工","DTYPE":null},{"_id":"69","AC_NO":"10502454","ST_NO":"0","SNO":"5","APPMODE":"5","X":"308298.763","Y":"2770813.177","APPTIME":"1051020110446","APP_NAME":"新工處","C_NAME":"信義","ADDR":"松山路(永吉路至忠孝東路5段)","CB_DA":"1051014","CE_DA":"1051024","CO_TI":null,"TC_MA":"黃笙瑋","TC_TL":"0986606775","TC_MA3":"闕詩芸","TC_TL3":"0912098677","NPURP":"道路維護施工","DTYPE":null},{"_id":"70","AC_NO":"10502482","ST_NO":"0","SNO":"4","APPMODE":"5","X":"304535.395","Y":"2771122.983","APPTIME":"1051020094426","APP_NAME":"新工處","C_NAME":"中山","ADDR":"龍江路11巷側溝蓋更新工程","CB_DA":"1051017","CE_DA":"1051107","CO_TI":null,"TC_MA":"黃昱豪","TC_TL":"0916983405","TC_MA3":"連建聰","TC_TL3":"0939608581","NPURP":"道路維護施工","DTYPE":null},{"_id":"71","AC_NO":"10502483","ST_NO":"0","SNO":"5","APPMODE":"5","X":"302655.497","Y":"2772508.514","APPTIME":"1051020093652","APP_NAME":"新工處","C_NAME":"中山","ADDR":"中山北路2段96巷側溝蓋更新工程","CB_DA":"1051017","CE_DA":"1051107","CO_TI":null,"TC_MA":"黃昱豪","TC_TL":"0916983405","TC_MA3":"連建聰","TC_TL3":"0939608581","NPURP":"道路維護施工","DTYPE":null},{"_id":"72","AC_NO":"10502493","ST_NO":"0","SNO":"1","APPMODE":"5","X":"305938.845","Y":"2769487.615","APPTIME":"1051020093557","APP_NAME":"新工處","C_NAME":"大安","ADDR":"信義路4段294巷〈信義路4段至文昌街〉","CB_DA":"1051019","CE_DA":"1051127","CO_TI":null,"TC_MA":"賈壽堂","TC_TL":"0922707315","TC_MA3":"鄭凱丞","TC_TL3":"0985060014","NPURP":"道路維護施工","DTYPE":null},{"_id":"73","AC_NO":"10502516","ST_NO":"0","SNO":"2","APPMODE":"5","X":"304839.776","Y":"2771945.493","APPTIME":"1051020090033","APP_NAME":"新工處","C_NAME":"中山","ADDR":"長春路327巷東側、遼寧街209巷側溝蓋更新工程","CB_DA":"1051020","CE_DA":"1051110","CO_TI":null,"TC_MA":"黃昱豪","TC_TL":"0916983405","TC_MA3":"連建聰","TC_TL3":"0939608581","NPURP":"道路維護施工","DTYPE":null},{"_id":"74","AC_NO":"10502520","ST_NO":"0","SNO":"1","APPMODE":"5","X":"306084.474","Y":"2772022.113","APPTIME":"1051020092737","APP_NAME":"新工處","C_NAME":"松山","ADDR":"龍田里光復北路155巷、延壽街402巷3、4弄及356巷4弄本線","CB_DA":"1051020","CE_DA":"1051103","CO_TI":null,"TC_MA":"杜婕菲","TC_TL":"0987512657","TC_MA3":"陳建竣","TC_TL3":"0989168070","NPURP":"道路維護施工","DTYPE":null},{"_id":"75","AC_NO":"1052036633","ST_NO":"0","SNO":"2","APPMODE":"6","X":"305700.004","Y":"2779373.081","APPTIME":"1051020095554","APP_NAME":"電信士林","C_NAME":"士林","ADDR":"仰德大道3段119號前及日本交流協會前","CB_DA":"1051018","CE_DA":"1051020","CO_TI":"09:30-16:00","TC_MA":"紀弘亮","TC_TL":"0910380815","TC_MA3":"張培莘","TC_TL3":"0910364533","NPURP":"人手孔施工","DTYPE":null},{"_id":"76","AC_NO":"AE1050164","ST_NO":"0","SNO":"4","APPMODE":"4","X":"300753.531","Y":"2779589.803","APPTIME":"1051020091927","APP_NAME":"水利處","C_NAME":"北投","ADDR":"公館路228巷口(奇岩里)","CB_DA":"1051012","CE_DA":"1051021","CO_TI":null,"TC_MA":"游貽任","TC_TL":"0931140233","TC_MA3":"陳言杰","TC_TL3":"0980047077","NPURP":"搶修","DTYPE":null},{"_id":"77","AC_NO":"AE1050167","ST_NO":"0","SNO":"1","APPMODE":"4","X":"301625.742","Y":"2771856.694","APPTIME":"1051020093506","APP_NAME":"水利處","C_NAME":"大同","ADDR":"南京西路延平北路口","CB_DA":"1051020","CE_DA":"1051031","CO_TI":null,"TC_MA":"鄭木祥","TC_TL":"0978552038","TC_MA3":"姚承維","TC_TL3":"0917796098","NPURP":"搶修","DTYPE":null},{"_id":"78","AC_NO":"GT1050353","ST_NO":"0","SNO":"1","APPMODE":"4","X":"303249.063","Y":"2772073.572","APPTIME":"1051020095900","APP_NAME":"大台北瓦斯","C_NAME":"中山","ADDR":"新生北路2段51號前","CB_DA":"1051020","CE_DA":"1051024","CO_TI":null,"TC_MA":"陳威仁","TC_TL":"0910016158","TC_MA3":"陳威仁","TC_TL3":"0910016158","NPURP":"搶修","DTYPE":null},{"_id":"79","AC_NO":"TH1050019","ST_NO":"0","SNO":"1","APPMODE":"4","X":"300247.922","Y":"2780678.596","APPTIME":"1051020110217","APP_NAME":"電信士林","C_NAME":"北投","ADDR":"育仁路68號旁","CB_DA":"1051020","CE_DA":"1051020","CO_TI":null,"TC_MA":"王芬滄","TC_TL":"0937026747","TC_MA3":"李益福","TC_TL3":"0917183688","NPURP":"搶修","DTYPE":null},{"_id":"80","AC_NO":"WE1050469","ST_NO":"0","SNO":"1","APPMODE":"4","X":"307965.723","Y":"2775106.574","APPTIME":"1051020094615","APP_NAME":"自來水東區","C_NAME":"內湖","ADDR":"港華街50號","CB_DA":"1051020","CE_DA":"1051020","CO_TI":null,"TC_MA":"吳幸璋","TC_TL":"0979213239","TC_MA3":"胡瑋峰","TC_TL3":"0916362203","NPURP":"搶修","DTYPE":null},{"_id":"81","AC_NO":"WE1050470","ST_NO":"0","SNO":"1","APPMODE":"4","X":"308114.853","Y":"2771297.226","APPTIME":"1051020112714","APP_NAME":"自來水東區","C_NAME":"信義","ADDR":"虎林街17號旁","CB_DA":"1051020","CE_DA":"1051020","CO_TI":null,"TC_MA":"董士誠","TC_TL":"0979213238","TC_MA3":"洪谷泰","TC_TL3":"0988321932","NPURP":"搶修","DTYPE":null},{"_id":"82","AC_NO":"WE1050471","ST_NO":"0","SNO":"1","APPMODE":"4","X":"304026.599","Y":"2772519.339","APPTIME":"1051020113525","APP_NAME":"自來水東區","C_NAME":"中山","ADDR":"民生東路2段147巷11弄14號旁","CB_DA":"1051020","CE_DA":"1051020","CO_TI":null,"TC_MA":"董士誠","TC_TL":"0979213238","TC_MA3":"劉育昌","TC_TL3":"0963583315","NPURP":"搶修","DTYPE":null}]}}